ceiec/__init__.py
ceiec/ceiec.py
ceiec-0.5.dist-info/METADATA
ceiec-0.5.dist-info/WHEEL
ceiec-0.5.dist-info/top_level.txt
ceiec-0.5.dist-info/RECORD
