Metadata-Version: 2.1
Name: ceiec
Version: 0.5
Summary: Paquete para uso exclusivo de miembros del CEIEC
Author: CEIEC members
Author-email: <ceiec@ceiec.com>
Keywords: python,CEIEC
Classifier: Development Status :: 1 - Planning
Classifier: Intended Audience :: Developers
Classifier: Programming Language :: Python :: 3
Classifier: Operating System :: Unix
Classifier: Operating System :: MacOS :: MacOS X
Classifier: Operating System :: Microsoft :: Windows
